{
  "$schema": "https://mintlify.com/docs.json",
  "theme": "mint",
  "name": "Trophy Documentation",
  "icons": {
    "library": "lucide"
  },
  "colors": {
    "primary": "#4CC74A",
    "light": "#4CC74A",
    "dark": "#4CC74A"
  },
  "background": {
    "color": {
      "light": "#F9F9FB",
      "dark": "#181818"
    }
  },
  "favicon": "/favicon.ico",
  "navigation": {
    "tabs": [
      {
        "tab": "Home",
        "groups": [
          {
            "group": "Getting Started",
            "pages": [
              "getting-started/introduction",
              "getting-started/quickstart"
            ]
          },
          {
            "group": "Platform",
            "pages": [
              "platform/overview",
              "platform/metrics",
              "platform/events",
              "platform/users",
              "platform/achievements",
              "platform/streaks",
              "platform/emails"
            ]
          },
          {
            "group": "Experimentation",
            "pages": [
              "experimentation/overview",
              "experimentation/trophy-impact-score"
            ]
          }
        ]
      },
      {
        "tab": "API Definition",
        "groups": [
          {
            "group": "Overview",
            "pages": [
              "api-reference/introduction",
              "api-reference/authentication",
              "api-reference/rate-limiting",
              "api-reference/client-libraries"
            ]
          },
          {
            "group": "Achievements",
            "pages": [
              "api-reference/endpoints/achievements/mark-an-achievement-as-completed"
            ]
          },
          {
            "group": "Metrics",
            "pages": [
              "api-reference/endpoints/metrics/send-a-metric-change-event"
            ]
          },
          {
            "group": "Users",
            "pages": [
              "api-reference/endpoints/users/identify-a-new-user",
              "api-reference/endpoints/users/get-a-single-user",
              "api-reference/endpoints/users/update-a-user",
              "api-reference/endpoints/users/get-all-metrics-for-a-user",
              "api-reference/endpoints/users/get-a-single-metric-for-a-user",
              "api-reference/endpoints/users/get-a-users-completed-achievements",
              "api-reference/endpoints/users/get-a-users-streak"
            ]
          }
        ]
      }
    ],
    "global": {
      "anchors": [
        {
          "anchor": "GitHub",
          "href": "https://github.com/trophyso",
          "icon": "github"
        },
        {
          "anchor": "Status",
          "href": "https://status.trophy.so",
          "icon": "radio-tower"
        },
        {
          "anchor": "Help",
          "href": "mailto:support@trophy.so",
          "icon": "life-buoy"
        }
      ]
    }
  },
  "logo": {
    "light": "/logo/logo_light.svg",
    "dark": "/logo/logo_dark.svg",
    "href": "https://trophy.so"
  },
  "navbar": {
    "links": [
      {
        "label": "Dashboard",
        "href": "https://app.trophy.so"
      }
    ],
    "primary": {
      "type": "button",
      "label": "Start for free",
      "href": "https://app.trophy.so/sign-up?utm_source=docs&utm_medium=navbar-links"
    }
  },
  "footer": {
    "socials": {
      "x": "https://x.com/trophylabs",
      "github": "https://github.com/trophyso",
      "youtube": "https://youtube.com/@trophylabsinc",
      "linkedin": "https://linkedin.com/company/trophylabs"
    }
  }
}
